yara.pyd
rekall_yara/__init__.py
rekall_yara-3.4.0.1.dist-info/DESCRIPTION.rst
rekall_yara-3.4.0.1.dist-info/METADATA
rekall_yara-3.4.0.1.dist-info/RECORD
rekall_yara-3.4.0.1.dist-info/WHEEL
rekall_yara-3.4.0.1.dist-info/metadata.json
rekall_yara-3.4.0.1.dist-info/top_level.txt
