Metadata-Version: 2.0
Name: rekall-yara
Version: 3.4.0.1
Summary: UNKNOWN
Home-page: http://www.rekall-forensic.com
Author: Victor M. Alvarez
Author-email: plusvic@gmail.com;vmalvarez@virustotal.com
License: UNKNOWN
Platform: UNKNOWN
